Workbook

Sheet Data
A1: 日期 | B1: 区域 | C1: 产品 | D1: 销量(件) | E1: 单价(元) | F1: 收入(元)
A2: 45292 | B2: 华东 | C2: Alpha | D2: 2156 | E2: =INDEX(Assumptions!$E$4:$E$8,MATCH($C2,Assumptions!$D$4:$D$8,0))*(1+Assumptions!$B$10)^((YEAR($A2)-2024)) -> 129 | F2: =D2*E2 -> 278124
A3: 45292 | B3: 华东 | C3: Beta | D3: 1597 | E3: =INDEX(Assumptions!$E$4:$E$8,MATCH($C3,Assumptions!$D$4:$D$8,0))*(1+Assumptions!$B$10)^((YEAR($A3)-2024)) -> 169 | F3: =D3*E3 -> 269893
A4: 45292 | B4: 华东 | C4: Gamma | D4: 1640 | E4: =INDEX(Assumptions!$E$4:$E$8,MATCH($C4,Assumptions!$D$4:$D$8,0))*(1+Assumptions!$B$10)^((YEAR($A4)-2024)) -> 199 | F4: =D4*E4 -> 326360
A5: 45292 | B5: 华东 | C5: Delta | D5: 1328 | E5: =INDEX(Assumptions!$E$4:$E$8,MATCH($C5,Assumptions!$D$4:$D$8,0))*(1+Assumptions!$B$10)^((YEAR($A5)-2024)) -> 249 | F5: =D5*E5 -> 330672
A6: 45292 | B6: 华东 | C6: Epsilon | D6: 1219 | E6: =INDEX(Assumptions!$E$4:$E$8,MATCH($C6,Assumptions!$D$4:$D$8,0))*(1+Assumptions!$B$10)^((YEAR($A6)-2024)) -> 299 | F6: =D6*E6 -> 364481
A7: 45292 | B7: 华南 | C7: Alpha | D7: 1895 | E7: =INDEX(Assumptions!$E$4:$E$8,MATCH($C7,Assumptions!$D$4:$D$8,0))*(1+Assumptions!$B$10)^((YEAR($A7)-2024)) -> 129 | F7: =D7*E7 -> 244455
A8: 45292 | B8: 华南 | C8: Beta | D8: 1810 | E8: =INDEX(Assumptions!$E$4:$E$8,MATCH($C8,Assumptions!$D$4:$D$8,0))*(1+Assumptions!$B$10)^((YEAR($A8)-2024)) -> 169 | F8: =D8*E8 -> 305890
A9: 45292 | B9: 华南 | C9: Gamma | D9: 1340 | E9: =INDEX(Assumptions!$E$4:$E$8,MATCH($C9,Assumptions!$D$4:$D$8,0))*(1+Assumptions!$B$10)^((YEAR($A9)-2024)) -> 199 | F9: =D9*E9 -> 266660
A10: 45292 | B10: 华南 | C10: Delta | D10: 1230 | E10: =INDEX(Assumptions!$E$4:$E$8,MATCH($C10,Assumptions!$D$4:$D$8,0))*(1+Assumptions!$B$10)^((YEAR($A10)-2024)) -> 249 | F10: =D10*E10 -> 306270
A11: 45292 | B11: 华南 | C11: Epsilon | D11: 850 | E11: =INDEX(Assumptions!$E$4:$E$8,MATCH($C11,Assumptions!$D$4:$D$8,0))*(1+Assumptions!$B$10)^((YEAR($A11)-2024)) -> 299 | F11: =D11*E11 -> 254150
A12: 45292 | B12: 华北 | C12: Alpha | D12: 1483 | E12: =INDEX(Assumptions!$E$4:$E$8,MATCH($C12,Assumptions!$D$4:$D$8,0))*(1+Assumptions!$B$10)^((YEAR($A12)-2024)) -> 129 | F12: =D12*E12 -> 191307
A13: 45292 | B13: 华北 | C13: Beta | D13: 1460 | E13: =INDEX(Assumptions!$E$4:$E$8,MATCH($C13,Assumptions!$D$4:$D$8,0))*(1+Assumptions!$B$10)^((YEAR($A13)-2024)) -> 169 | F13: =D13*E13 -> 246740
... A361: 46023 | B361: 华北 | C361: Epsilon | D361: 764 | E361: =INDEX(Assumptions!$E$4:$E$8,MATCH($C361,Assumptions!$D$4:$D$8,0))*(1+Assumptions!$B$10)^((YEAR($A361)-2024)) -> 329.6475 | F361: =D361*E361 -> 251850.69

Sheet Assumptions
A1: 参数 | B1: 值
A2: 区域列表 | B2: （用于下拉选择）
A3: 区域 | B3: 说明 | D3: 产品 | E3: 基准单价(元)
A4: 华东 | B4: 销售区域 | D4: Alpha | E4: 129
A5: 华南 | B5: 销售区域 | D5: Beta | E5: 169
A6: 华北 | B6: 销售区域 | D6: Gamma | E6: 199
D7: Delta | E7: 249
D8: Epsilon | E8: 299
A10: 通胀/提价率(年) | B10: 0.05
A11: 销量季节性强度(0-1) | B11: 0.35

Sheet Analysis
A1: 销售仪表盘（公式驱动）
A3: 区域选择： | B3: 华东 | E3: 关键指标
E4: 24个月累计收入 | F4: =SUM(B7:B30) -> 38928679
A5: 月度收入(元) | E5: 最近12个月同比(收入) | F5: =IFERROR((SUM(B19:B30)/SUM(B7:B18))-1,"") -> -0.0013172629
A6: 月份 | B6: 收入 | C6: 环比 | E6: 波动率(环比标准差) | F6: =IFERROR(stdev.s(C8:C30),"")
A7: =DATE(2024,1,1)+0*31 -> 45292 | B7: =SUMIFS(Data!$F:$F,Data!$B:$B,$B$3,Data!$A:$A,DATE(YEAR($A7),MONTH($A7),1)) -> 1569530
A8: =DATE(2024,1,1)+1*31 -> 45323 | B8: =SUMIFS(Data!$F:$F,Data!$B:$B,$B$3,Data!$A:$A,DATE(YEAR($A8),MONTH($A8),1)) -> 1802966 | C8: =IFERROR((B8-B7)/B7,"") -> 0.14872987
A9: =DATE(2024,1,1)+2*31 -> 45354 | B9: =SUMIFS(Data!$F:$F,Data!$B:$B,$B$3,Data!$A:$A,DATE(YEAR($A9),MONTH($A9),1)) -> 2094359 | C9: =IFERROR((B9-B8)/B8,"") -> 0.16161869
A10: =DATE(2024,1,1)+3*31 -> 45385 | B10: =SUMIFS(Data!$F:$F,Data!$B:$B,$B$3,Data!$A:$A,DATE(YEAR($A10),MONTH($A10),1)) -> 1938900 | C10: =IFERROR((B10-B9)/B9,"") -> -0.074227484
A11: =DATE(2024,1,1)+4*31 -> 45416 | B11: =SUMIFS(Data!$F:$F,Data!$B:$B,$B$3,Data!$A:$A,DATE(YEAR($A11),MONTH($A11),1)) -> 2124368 | C11: =IFERROR((B11-B10)/B10,"") -> 0.0956563
A12: =DATE(2024,1,1)+5*31 -> 45447 | B12: =SUMIFS(Data!$F:$F,Data!$B:$B,$B$3,Data!$A:$A,DATE(YEAR($A12),MONTH($A12),1)) -> 1809056 | C12: =IFERROR((B12-B11)/B11,"") -> -0.14842626
A13: =DATE(2024,1,1)+6*31 -> 45478 | B13: =SUMIFS(Data!$F:$F,Data!$B:$B,$B$3,Data!$A:$A,DATE(YEAR($A13),MONTH($A13),1)) -> 1591262 | C13: =IFERROR((B13-B12)/B12,"") -> -0.12039097
A14: =DATE(2024,1,1)+7*31 -> 45509 | B14: =SUMIFS(Data!$F:$F,Data!$B:$B,$B$3,Data!$A:$A,DATE(YEAR($A14),MONTH($A14),1)) -> 1436493 | C14: =IFERROR((B14-B13)/B13,"") -> -0.097261796
A15: =DATE(2024,1,1)+8*31 -> 45540 | B15: =SUMIFS(Data!$F:$F,Data!$B:$B,$B$3,Data!$A:$A,DATE(YEAR($A15),MONTH($A15),1)) -> 1283919 | C15: =IFERROR((B15-B14)/B14,"") -> -0.10621284
A16: =DATE(2024,1,1)+9*31 -> 45571 | B16: =SUMIFS(Data!$F:$F,Data!$B:$B,$B$3,Data!$A:$A,DATE(YEAR($A16),MONTH($A16),1)) -> 1206506 | C16: =IFERROR((B16-B15)/B15,"") -> -0.060294302
A17: =DATE(2024,1,1)+10*31 -> 45602 | B17: =SUMIFS(Data!$F:$F,Data!$B:$B,$B$3,Data!$A:$A,DATE(YEAR($A17),MONTH($A17),1)) -> 1287290 | C17: =IFERROR((B17-B16)/B16,"") -> 0.066956982
A18: =DATE(2024,1,1)+11*31 -> 45633 | B18: =SUMIFS(Data!$F:$F,Data!$B:$B,$B$3,Data!$A:$A,DATE(YEAR($A18),MONTH($A18),1)) -> 1332519 | C18: =IFERROR((B18-B17)/B17,"") -> 0.035135051
A19: =DATE(2024,1,1)+12*31 -> 45664 | B19: =SUMIFS(Data!$F:$F,Data!$B:$B,$B$3,Data!$A:$A,DATE(YEAR($A19),MONTH($A19),1)) -> 1748276.2 | C19: =IFERROR((B19-B18)/B18,"") -> 0.3120085
A20: =DATE(2024,1,1)+13*31 -> 45695 | B20: =SUMIFS(Data!$F:$F,Data!$B:$B,$B$3,Data!$A:$A,DATE(YEAR($A20),MONTH($A20),1)) -> 2017067.9 | C20: =IFERROR((B20-B19)/B19,"") -> 0.15374664
A21: =DATE(2024,1,1)+14*31 -> 45726 | B21: =SUMIFS(Data!$F:$F,Data!$B:$B,$B$3,Data!$A:$A,DATE(YEAR($A21),MONTH($A21),1)) -> 2139084.1 | C21: =IFERROR((B21-B20)/B20,"") -> 0.060491917
A22: =DATE(2024,1,1)+15*31 -> 45757 | B22: =SUMIFS(Data!$F:$F,Data!$B:$B,$B$3,Data!$A:$A,DATE(YEAR($A22),MONTH($A22),1)) -> 2213979.6 | C22: =IFERROR((B22-B21)/B21,"") -> 0.035012858
A23: =DATE(2024,1,1)+16*31 -> 45788 | B23: =SUMIFS(Data!$F:$F,Data!$B:$B,$B$3,Data!$A:$A,DATE(YEAR($A23),MONTH($A23),1)) -> 2112317.5 | C23: =IFERROR((B23-B22)/B22,"") -> -0.045918242
A24: =DATE(2024,1,1)+17*31 -> 45819 | B24: =SUMIFS(Data!$F:$F,Data!$B:$B,$B$3,Data!$A:$A,DATE(YEAR($A24),MONTH($A24),1)) -> 1914902.9 | C24: =IFERROR((B24-B23)/B23,"") -> -0.093458817
A25: =DATE(2024,1,1)+18*31 -> 45850 | B25: =SUMIFS(Data!$F:$F,Data!$B:$B,$B$3,Data!$A:$A,DATE(YEAR($A25),MONTH($A25),1)) -> 1749527.9 | C25: =IFERROR((B25-B24)/B24,"") -> -0.086362084
A26: =DATE(2024,1,1)+19*31 -> 45881 | B26: =SUMIFS(Data!$F:$F,Data!$B:$B,$B$3,Data!$A:$A,DATE(YEAR($A26),MONTH($A26),1)) -> 1491957.6 | C26: =IFERROR((B26-B25)/B25,"") -> -0.14722272
A27: =DATE(2024,1,1)+20*31 -> 45912 | B27: =SUMIFS(Data!$F:$F,Data!$B:$B,$B$3,Data!$A:$A,DATE(YEAR($A27),MONTH($A27),1)) -> 0 | C27: =IFERROR((B27-B26)/B26,"") -> -1
A28: =DATE(2024,1,1)+21*31 -> 45943 | B28: =SUMIFS(Data!$F:$F,Data!$B:$B,$B$3,Data!$A:$A,DATE(YEAR($A28),MONTH($A28),1)) -> 1379749.4 | C28: =IFERROR((B28-B27)/B27,"")
A29: =DATE(2024,1,1)+22*31 -> 45974 | B29: =SUMIFS(Data!$F:$F,Data!$B:$B,$B$3,Data!$A:$A,DATE(YEAR($A29),MONTH($A29),1)) -> 1318061.9 | C29: =IFERROR((B29-B28)/B28,"") -> -0.044709208
A30: =DATE(2024,1,1)+23*31 -> 46005 | B30: =SUMIFS(Data!$F:$F,Data!$B:$B,$B$3,Data!$A:$A,DATE(YEAR($A30),MONTH($A30),1)) -> 1366586.6 | C30: =IFERROR((B30-B29)/B29,"") -> 0.036815192
A32: 产品收入排行（当前区域）
A33: 产品 | B33: 累计收入(元)
A34: Alpha | B34: =SUMIFS(Data!$F:$F,Data!$B:$B,$B$3,Data!$C:$C,$A34) -> 6864570.2
A35: Beta | B35: =SUMIFS(Data!$F:$F,Data!$B:$B,$B$3,Data!$C:$C,$A35) -> 7715161.8
A36: Gamma | B36: =SUMIFS(Data!$F:$F,Data!$B:$B,$B$3,Data!$C:$C,$A36) -> 8698248.7
A37: Delta | B37: =SUMIFS(Data!$F:$F,Data!$B:$B,$B$3,Data!$C:$C,$A37) -> 8948375.9
A38: Epsilon | B38: =SUMIFS(Data!$F:$F,Data!$B:$B,$B$3,Data!$C:$C,$A38) -> 8330593
