Workbook

Sheet Data
A1: 日期 | B1: 区域 | C1: 产品 | D1: 销量(件) | E1: 单价(元) | F1: 收入(元)
A2: 45292 | B2: 华东 | C2: Alpha | D2: 2156 | E2: =INDEX(Assumptions!$E$4:$E$8,MATCH($C2,Assumptions!$D$4:$D$8,0))*(1+Assumptions!$B$10)^((YEAR($A2)-2024))*(1-Assumptions!$B$12) | F2: =D2*E2
A3: 45292 | B3: 华东 | C3: Beta | D3: 1597 | E3: =INDEX(Assumptions!$E$4:$E$8,MATCH($C3,Assumptions!$D$4:$D$8,0))*(1+Assumptions!$B$10)^((YEAR($A3)-2024))*(1-Assumptions!$B$12) | F3: =D3*E3
A4: 45292 | B4: 华东 | C4: Gamma | D4: 1640 | E4: =INDEX(Assumptions!$E$4:$E$8,MATCH($C4,Assumptions!$D$4:$D$8,0))*(1+Assumptions!$B$10)^((YEAR($A4)-2024))*(1-Assumptions!$B$12) | F4: =D4*E4
A5: 45292 | B5: 华东 | C5: Delta | D5: 1328 | E5: =INDEX(Assumptions!$E$4:$E$8,MATCH($C5,Assumptions!$D$4:$D$8,0))*(1+Assumptions!$B$10)^((YEAR($A5)-2024))*(1-Assumptions!$B$12) | F5: =D5*E5
A6: 45292 | B6: 华东 | C6: Epsilon | D6: 1219 | E6: =INDEX(Assumptions!$E$4:$E$8,MATCH($C6,Assumptions!$D$4:$D$8,0))*(1+Assumptions!$B$10)^((YEAR($A6)-2024))*(1-Assumptions!$B$12) | F6: =D6*E6
A7: 45292 | B7: 华南 | C7: Alpha | D7: 1895 | E7: =INDEX(Assumptions!$E$4:$E$8,MATCH($C7,Assumptions!$D$4:$D$8,0))*(1+Assumptions!$B$10)^((YEAR($A7)-2024))*(1-Assumptions!$B$12) | F7: =D7*E7
A8: 45292 | B8: 华南 | C8: Beta | D8: 1810 | E8: =INDEX(Assumptions!$E$4:$E$8,MATCH($C8,Assumptions!$D$4:$D$8,0))*(1+Assumptions!$B$10)^((YEAR($A8)-2024))*(1-Assumptions!$B$12) | F8: =D8*E8
A9: 45292 | B9: 华南 | C9: Gamma | D9: 1340 | E9: =INDEX(Assumptions!$E$4:$E$8,MATCH($C9,Assumptions!$D$4:$D$8,0))*(1+Assumptions!$B$10)^((YEAR($A9)-2024))*(1-Assumptions!$B$12) | F9: =D9*E9
A10: 45292 | B10: 华南 | C10: Delta | D10: 1230 | E10: =INDEX(Assumptions!$E$4:$E$8,MATCH($C10,Assumptions!$D$4:$D$8,0))*(1+Assumptions!$B$10)^((YEAR($A10)-2024))*(1-Assumptions!$B$12) | F10: =D10*E10
A11: 45292 | B11: 华南 | C11: Epsilon | D11: 850 | E11: =INDEX(Assumptions!$E$4:$E$8,MATCH($C11,Assumptions!$D$4:$D$8,0))*(1+Assumptions!$B$10)^((YEAR($A11)-2024))*(1-Assumptions!$B$12) | F11: =D11*E11
A12: 45292 | B12: 华北 | C12: Alpha | D12: 1483 | E12: =INDEX(Assumptions!$E$4:$E$8,MATCH($C12,Assumptions!$D$4:$D$8,0))*(1+Assumptions!$B$10)^((YEAR($A12)-2024))*(1-Assumptions!$B$12) | F12: =D12*E12
A13: 45292 | B13: 华北 | C13: Beta | D13: 1460 | E13: =INDEX(Assumptions!$E$4:$E$8,MATCH($C13,Assumptions!$D$4:$D$8,0))*(1+Assumptions!$B$10)^((YEAR($A13)-2024))*(1-Assumptions!$B$12) | F13: =D13*E13
... A361: 46023 | B361: 华北 | C361: Epsilon | D361: 764 | E361: =INDEX(Assumptions!$E$4:$E$8,MATCH($C361,Assumptions!$D$4:$D$8,0))*(1+Assumptions!$B$10)^((YEAR($A361)-2024))*(1-Assumptions!$B$12) | F361: =D361*E361

Sheet Assumptions
A1: 参数 | B1: 值
A2: 区域列表 | B2: （用于下拉选择）
A3: 区域 | B3: 说明 | D3: 产品 | E3: 基准单价(元)
A4: 华东 | B4: 销售区域 | D4: Alpha | E4: 129
A5: 华南 | B5: 销售区域 | D5: Beta | E5: 169
A6: 华北 | B6: 销售区域 | D6: Gamma | E6: 199
D7: Delta | E7: 249
D8: Epsilon | E8: 299
A10: 通胀/提价率(年) | B10: =INDEX($B$15:$B$17, MATCH(Analysis!$B$4, $A$15:$A$17, 0))
A11: 销量季节性强度(0-1) | B11: 0.35
A12: 折扣率(情景驱动) | B12: =INDEX($C$15:$C$17, MATCH(Analysis!$B$4, $A$15:$A$17, 0))
A13: 情景参数（Scenario）
A14: 情景 | B14: 通胀/提价率(年) | C14: 折扣率 | D14: 备注
A15: 基准 | B15: 0.05 | C15: 0 | D15: 默认
A16: 乐观 | B16: 0.08 | C16: 0.02 | D16: 更高提价 + 小折扣促销
A17: 压力 | B17: 0.02 | C17: 0.05 | D17: 低提价 + 让利换量

Sheet Analysis
A1: 销售仪表盘（公式驱动）
A2: 快速入口： | B2: 打开交互版（HTML） | C2: 打开 PDF 版本 | D2: =HYPERLINK("ms-powerpoint:ofe|u|"&"file:///"&IF(LEFT(SUBSTITUTE(SUBSTITUTE(LEFT(CELL("filename",$A$1),FIND("[",CELL("filename",$A$1))-1),"\\","/")," ","%20"),1)="/",MID(SUBSTITUTE(SUBSTITUTE(LEFT(CELL("filename",$A$1),FIND("[",CELL("filename",$A$1))-1),"\\","/")," ","%20"),2,999),SUBSTITUTE(SUBSTITUTE(LEFT(CELL("filename",$A$1),FIND("[",CELL("filename",$A$1))-1),"\\","/")," ","%20"))&"MTC_能力演示.pptx","打开 PPT 演示")
A3: 区域选择： | B3: 华东 | C3: 产品选择： | D3: Alpha | E3: 关键指标 | F3: 值
A4: 情景选择： | B4: 基准 | E4: 24个月累计收入 | F4: =SUM(B7:B30)
A5: 月度收入(元) | E5: 最近12个月同比(收入) | F5: =IFERROR((SUM(B19:B30)/SUM(B7:B18))-1,"")
A6: 月份 | B6: 收入 | C6: 环比 | D6: 产品收入(元) | E6: 波动率(环比标准差) | F6: =IFERROR(stdev.s(C8:C30),"")
A7: =DATE(2024,1,1)+0*31 | B7: =SUMIFS(Data!$F:$F,Data!$B:$B,$B$3,Data!$A:$A,DATE(YEAR($A7),MONTH($A7),1)) | D7: =SUMIFS(Data!$F:$F,Data!$B:$B,$B$3,Data!$C:$C,$D$3,Data!$A:$A,DATE(YEAR($A7),MONTH($A7),1))
A8: =DATE(2024,1,1)+1*31 | B8: =SUMIFS(Data!$F:$F,Data!$B:$B,$B$3,Data!$A:$A,DATE(YEAR($A8),MONTH($A8),1)) | C8: =IFERROR((B8-B7)/B7,"") | D8: =SUMIFS(Data!$F:$F,Data!$B:$B,$B$3,Data!$C:$C,$D$3,Data!$A:$A,DATE(YEAR($A8),MONTH($A8),1))
A9: =DATE(2024,1,1)+2*31 | B9: =SUMIFS(Data!$F:$F,Data!$B:$B,$B$3,Data!$A:$A,DATE(YEAR($A9),MONTH($A9),1)) | C9: =IFERROR((B9-B8)/B8,"") | D9: =SUMIFS(Data!$F:$F,Data!$B:$B,$B$3,Data!$C:$C,$D$3,Data!$A:$A,DATE(YEAR($A9),MONTH($A9),1))
A10: =DATE(2024,1,1)+3*31 | B10: =SUMIFS(Data!$F:$F,Data!$B:$B,$B$3,Data!$A:$A,DATE(YEAR($A10),MONTH($A10),1)) | C10: =IFERROR((B10-B9)/B9,"") | D10: =SUMIFS(Data!$F:$F,Data!$B:$B,$B$3,Data!$C:$C,$D$3,Data!$A:$A,DATE(YEAR($A10),MONTH($A10),1))
A11: =DATE(2024,1,1)+4*31 | B11: =SUMIFS(Data!$F:$F,Data!$B:$B,$B$3,Data!$A:$A,DATE(YEAR($A11),MONTH($A11),1)) | C11: =IFERROR((B11-B10)/B10,"") | D11: =SUMIFS(Data!$F:$F,Data!$B:$B,$B$3,Data!$C:$C,$D$3,Data!$A:$A,DATE(YEAR($A11),MONTH($A11),1))
A12: =DATE(2024,1,1)+5*31 | B12: =SUMIFS(Data!$F:$F,Data!$B:$B,$B$3,Data!$A:$A,DATE(YEAR($A12),MONTH($A12),1)) | C12: =IFERROR((B12-B11)/B11,"") | D12: =SUMIFS(Data!$F:$F,Data!$B:$B,$B$3,Data!$C:$C,$D$3,Data!$A:$A,DATE(YEAR($A12),MONTH($A12),1))
A13: =DATE(2024,1,1)+6*31 | B13: =SUMIFS(Data!$F:$F,Data!$B:$B,$B$3,Data!$A:$A,DATE(YEAR($A13),MONTH($A13),1)) | C13: =IFERROR((B13-B12)/B12,"") | D13: =SUMIFS(Data!$F:$F,Data!$B:$B,$B$3,Data!$C:$C,$D$3,Data!$A:$A,DATE(YEAR($A13),MONTH($A13),1))
A14: =DATE(2024,1,1)+7*31 | B14: =SUMIFS(Data!$F:$F,Data!$B:$B,$B$3,Data!$A:$A,DATE(YEAR($A14),MONTH($A14),1)) | C14: =IFERROR((B14-B13)/B13,"") | D14: =SUMIFS(Data!$F:$F,Data!$B:$B,$B$3,Data!$C:$C,$D$3,Data!$A:$A,DATE(YEAR($A14),MONTH($A14),1))
A15: =DATE(2024,1,1)+8*31 | B15: =SUMIFS(Data!$F:$F,Data!$B:$B,$B$3,Data!$A:$A,DATE(YEAR($A15),MONTH($A15),1)) | C15: =IFERROR((B15-B14)/B14,"") | D15: =SUMIFS(Data!$F:$F,Data!$B:$B,$B$3,Data!$C:$C,$D$3,Data!$A:$A,DATE(YEAR($A15),MONTH($A15),1))
A16: =DATE(2024,1,1)+9*31 | B16: =SUMIFS(Data!$F:$F,Data!$B:$B,$B$3,Data!$A:$A,DATE(YEAR($A16),MONTH($A16),1)) | C16: =IFERROR((B16-B15)/B15,"") | D16: =SUMIFS(Data!$F:$F,Data!$B:$B,$B$3,Data!$C:$C,$D$3,Data!$A:$A,DATE(YEAR($A16),MONTH($A16),1))
A17: =DATE(2024,1,1)+10*31 | B17: =SUMIFS(Data!$F:$F,Data!$B:$B,$B$3,Data!$A:$A,DATE(YEAR($A17),MONTH($A17),1)) | C17: =IFERROR((B17-B16)/B16,"") | D17: =SUMIFS(Data!$F:$F,Data!$B:$B,$B$3,Data!$C:$C,$D$3,Data!$A:$A,DATE(YEAR($A17),MONTH($A17),1))
A18: =DATE(2024,1,1)+11*31 | B18: =SUMIFS(Data!$F:$F,Data!$B:$B,$B$3,Data!$A:$A,DATE(YEAR($A18),MONTH($A18),1)) | C18: =IFERROR((B18-B17)/B17,"") | D18: =SUMIFS(Data!$F:$F,Data!$B:$B,$B$3,Data!$C:$C,$D$3,Data!$A:$A,DATE(YEAR($A18),MONTH($A18),1))
A19: =DATE(2024,1,1)+12*31 | B19: =SUMIFS(Data!$F:$F,Data!$B:$B,$B$3,Data!$A:$A,DATE(YEAR($A19),MONTH($A19),1)) | C19: =IFERROR((B19-B18)/B18,"") | D19: =SUMIFS(Data!$F:$F,Data!$B:$B,$B$3,Data!$C:$C,$D$3,Data!$A:$A,DATE(YEAR($A19),MONTH($A19),1))
A20: =DATE(2024,1,1)+13*31 | B20: =SUMIFS(Data!$F:$F,Data!$B:$B,$B$3,Data!$A:$A,DATE(YEAR($A20),MONTH($A20),1)) | C20: =IFERROR((B20-B19)/B19,"") | D20: =SUMIFS(Data!$F:$F,Data!$B:$B,$B$3,Data!$C:$C,$D$3,Data!$A:$A,DATE(YEAR($A20),MONTH($A20),1))
A21: =DATE(2024,1,1)+14*31 | B21: =SUMIFS(Data!$F:$F,Data!$B:$B,$B$3,Data!$A:$A,DATE(YEAR($A21),MONTH($A21),1)) | C21: =IFERROR((B21-B20)/B20,"") | D21: =SUMIFS(Data!$F:$F,Data!$B:$B,$B$3,Data!$C:$C,$D$3,Data!$A:$A,DATE(YEAR($A21),MONTH($A21),1))
A22: =DATE(2024,1,1)+15*31 | B22: =SUMIFS(Data!$F:$F,Data!$B:$B,$B$3,Data!$A:$A,DATE(YEAR($A22),MONTH($A22),1)) | C22: =IFERROR((B22-B21)/B21,"") | D22: =SUMIFS(Data!$F:$F,Data!$B:$B,$B$3,Data!$C:$C,$D$3,Data!$A:$A,DATE(YEAR($A22),MONTH($A22),1))
A23: =DATE(2024,1,1)+16*31 | B23: =SUMIFS(Data!$F:$F,Data!$B:$B,$B$3,Data!$A:$A,DATE(YEAR($A23),MONTH($A23),1)) | C23: =IFERROR((B23-B22)/B22,"") | D23: =SUMIFS(Data!$F:$F,Data!$B:$B,$B$3,Data!$C:$C,$D$3,Data!$A:$A,DATE(YEAR($A23),MONTH($A23),1))
A24: =DATE(2024,1,1)+17*31 | B24: =SUMIFS(Data!$F:$F,Data!$B:$B,$B$3,Data!$A:$A,DATE(YEAR($A24),MONTH($A24),1)) | C24: =IFERROR((B24-B23)/B23,"") | D24: =SUMIFS(Data!$F:$F,Data!$B:$B,$B$3,Data!$C:$C,$D$3,Data!$A:$A,DATE(YEAR($A24),MONTH($A24),1))
A25: =DATE(2024,1,1)+18*31 | B25: =SUMIFS(Data!$F:$F,Data!$B:$B,$B$3,Data!$A:$A,DATE(YEAR($A25),MONTH($A25),1)) | C25: =IFERROR((B25-B24)/B24,"") | D25: =SUMIFS(Data!$F:$F,Data!$B:$B,$B$3,Data!$C:$C,$D$3,Data!$A:$A,DATE(YEAR($A25),MONTH($A25),1))
A26: =DATE(2024,1,1)+19*31 | B26: =SUMIFS(Data!$F:$F,Data!$B:$B,$B$3,Data!$A:$A,DATE(YEAR($A26),MONTH($A26),1)) | C26: =IFERROR((B26-B25)/B25,"") | D26: =SUMIFS(Data!$F:$F,Data!$B:$B,$B$3,Data!$C:$C,$D$3,Data!$A:$A,DATE(YEAR($A26),MONTH($A26),1))
A27: =DATE(2024,1,1)+20*31 | B27: =SUMIFS(Data!$F:$F,Data!$B:$B,$B$3,Data!$A:$A,DATE(YEAR($A27),MONTH($A27),1)) | C27: =IFERROR((B27-B26)/B26,"") | D27: =SUMIFS(Data!$F:$F,Data!$B:$B,$B$3,Data!$C:$C,$D$3,Data!$A:$A,DATE(YEAR($A27),MONTH($A27),1))
A28: =DATE(2024,1,1)+21*31 | B28: =SUMIFS(Data!$F:$F,Data!$B:$B,$B$3,Data!$A:$A,DATE(YEAR($A28),MONTH($A28),1)) | C28: =IFERROR((B28-B27)/B27,"") | D28: =SUMIFS(Data!$F:$F,Data!$B:$B,$B$3,Data!$C:$C,$D$3,Data!$A:$A,DATE(YEAR($A28),MONTH($A28),1))
A29: =DATE(2024,1,1)+22*31 | B29: =SUMIFS(Data!$F:$F,Data!$B:$B,$B$3,Data!$A:$A,DATE(YEAR($A29),MONTH($A29),1)) | C29: =IFERROR((B29-B28)/B28,"") | D29: =SUMIFS(Data!$F:$F,Data!$B:$B,$B$3,Data!$C:$C,$D$3,Data!$A:$A,DATE(YEAR($A29),MONTH($A29),1))
A30: =DATE(2024,1,1)+23*31 | B30: =SUMIFS(Data!$F:$F,Data!$B:$B,$B$3,Data!$A:$A,DATE(YEAR($A30),MONTH($A30),1)) | C30: =IFERROR((B30-B29)/B29,"") | D30: =SUMIFS(Data!$F:$F,Data!$B:$B,$B$3,Data!$C:$C,$D$3,Data!$A:$A,DATE(YEAR($A30),MONTH($A30),1))
A32: 产品收入排行（当前区域）
A33: 产品 | B33: 累计收入(元)
A34: Alpha | B34: =SUMIFS(Data!$F:$F,Data!$B:$B,$B$3,Data!$C:$C,$A34)
A35: Beta | B35: =SUMIFS(Data!$F:$F,Data!$B:$B,$B$3,Data!$C:$C,$A35)
A36: Gamma | B36: =SUMIFS(Data!$F:$F,Data!$B:$B,$B$3,Data!$C:$C,$A36)
A37: Delta | B37: =SUMIFS(Data!$F:$F,Data!$B:$B,$B$3,Data!$C:$C,$A37)
A38: Epsilon | B38: =SUMIFS(Data!$F:$F,Data!$B:$B,$B$3,Data!$C:$C,$A38)

Sheet QualityGate
A1: 数据质量门禁（Poka‑Yoke）
A2: 总状态： | B2: =IF(COUNTIF(D4:D8,"FAIL")>0,"FAIL","PASS")
A3: 检查项 | B3: 公式 | C3: 当前值 | D3: 判定
A4: 日期缺失 | B4: =COUNTBLANK(Data!A2:A361) | C4: =COUNTBLANK(Data!A2:A361) | D4: =IF(C4<=0,"PASS","FAIL")
A5: 区域缺失 | B5: =COUNTBLANK(Data!B2:B361) | C5: =COUNTBLANK(Data!B2:B361) | D5: =IF(C5<=0,"PASS","FAIL")
A6: 产品缺失 | B6: =COUNTBLANK(Data!C2:C361) | C6: =COUNTBLANK(Data!C2:C361) | D6: =IF(C6<=0,"PASS","FAIL")
A7: 销量<=0 | B7: =COUNTIF(Data!D2:D361,"<=0") | C7: =COUNTIF(Data!D2:D361,"<=0") | D7: =IF(C7<=0,"PASS","FAIL")
A8: 收入<=0 | B8: =COUNTIF(Data!F2:F361,"<=0") | C8: =COUNTIF(Data!F2:F361,"<=0") | D8: =IF(C8<=0,"PASS","FAIL")

Sheet Explain
A1: Explain / 方法说明（给人看的 Excel）
A3: 1) 这份模型展示了什么？
A4: • 多表联动：Data（明细）→ Analysis（仪表盘）
A5: • 情景（Scenario）驱动：选择“基准/乐观/压力”，通胀与折扣会联动影响单价与收入
A6: • 数据质量门禁：QualityGate 给出 PASS/FAIL
A7: • 外部联动：Analysis 页提供本地 HTML / PDF / PPT 入口（超链接）
A9: 2) 关键公式链路（示例）
A10: Data!E（单价） = 基准单价 × (1+通胀)^(年份差) × (1-折扣)
A11: Data!F（收入） = 销量 × 单价
A12: Analysis!B（按月收入） = SUMIFS(Data!收入, 区域, 选中区域, 日期=当月)
